hello.py
greetuvm-0.0.1.dist-info/LICENSE.txt
greetuvm-0.0.1.dist-info/METADATA
greetuvm-0.0.1.dist-info/WHEEL
greetuvm-0.0.1.dist-info/top_level.txt
greetuvm-0.0.1.dist-info/RECORD
