Metadata-Version: 2.1
Name: greetuvm
Version: 0.0.1
Summary: Say hello to someone (or thing)
Home-page: https://gitlab.com/monden/greetuvm
Author: Monde
Author-email: xytuple@gmail.com
License: UNKNOWN
Platform: UNKNOWN
Classifier: Programming Language :: Python :: 3
Classifier: Programming Language :: Python :: 3.8
Classifier: License :: OSI Approved :: GNU General Public License v3 (GPLv3)
Provides-Extra: dev
Requires-Dist: pytest (>=3.7) ; extra == 'dev'
Requires-Dist: check-manifest (>=0.42) ; extra == 'dev'
Requires-Dist: twine (>=3.2.0) ; extra == 'dev'
